password_validator/__init__.py
password_validator/constants.py
password_validator/lib.py
password_validator/password_validator.py
password_validator-1.0.dist-info/LICENSE
password_validator-1.0.dist-info/METADATA
password_validator-1.0.dist-info/WHEEL
password_validator-1.0.dist-info/top_level.txt
password_validator-1.0.dist-info/RECORD
